async_postgres_watcher/__init__.py
async_postgres_watcher/watcher.py
casbin_async_postgres_watcher-1.4.0.dist-info/licenses/LICENSE
casbin_async_postgres_watcher-1.4.0.dist-info/METADATA
casbin_async_postgres_watcher-1.4.0.dist-info/WHEEL
casbin_async_postgres_watcher-1.4.0.dist-info/top_level.txt
casbin_async_postgres_watcher-1.4.0.dist-info/RECORD
